cutcut/__init__.py
cutcut/data/tag.txt
cutcut/data/vocab.txt
cutcut/savedModel/saved_model.pb
cutcut/savedModel/variables/variables.data-00000-of-00001
cutcut/savedModel/variables/variables.index
cutcut-0.0.2.dist-info/LICENSE
cutcut-0.0.2.dist-info/METADATA
cutcut-0.0.2.dist-info/WHEEL
cutcut-0.0.2.dist-info/top_level.txt
cutcut-0.0.2.dist-info/RECORD
