Metadata-Version: 2.1
Name: cutcut
Version: 0.0.2
Summary: General tokenizer
Home-page: https://github.com/ljv006/cutcut
Author: ljv006
Author-email: longjw6@qq.com
License: MIT
Platform: UNKNOWN
Classifier: Development Status :: 3 - Alpha
Classifier: Intended Audience :: Developers
Classifier: Topic :: Software Development :: Build Tools
Classifier: License :: OSI Approved :: MIT License
Classifier: Programming Language :: Python :: 3.6
Classifier: Programming Language :: Python :: 3.7
Classifier: Programming Language :: Python :: 3.8
Requires-Python: >=3.6
Requires-Dist: bert-for-tf2
Requires-Dist: tensorflow (>=2.0.0)
